androidpublisher/__init__.py
androidpublisher/__main__.py
androidpublisher/main.py
androidpublisher/upload.py
androidpublisher-0.1.10.dist-info/entry_points.txt
androidpublisher-0.1.10.dist-info/WHEEL
androidpublisher-0.1.10.dist-info/METADATA
androidpublisher-0.1.10.dist-info/RECORD
