Metadata-Version: 2.1
Name: androidpublisher
Version: 0.1.10
Summary: 
Author: leynier
Author-email: leynier41@gmail.com
Requires-Python: >=3.7,<4.0
Classifier: Programming Language :: Python :: 3
Classifier: Programming Language :: Python :: 3.7
Classifier: Programming Language :: Python :: 3.8
Classifier: Programming Language :: Python :: 3.9
Requires-Dist: google-api-python-client (>=2.27.0,<3.0.0)
Requires-Dist: oauth2client (>=4.1.3,<5.0.0)
Requires-Dist: six (>=1.16.0,<2.0.0)
Requires-Dist: typer (>=0.4.0,<0.5.0)
